elasticai_api/__init__.py
elasticai_api/common/__init__.py
elasticai_api/common/base_controller.py
elasticai_api/common/constants.py
elasticai_api/common/data_shard_service.py
elasticai_api/common/master_client.py
elasticai_api/common/resource_monitor.py
elasticai_api/common/synchronization.py
elasticai_api/io/__init__.py
elasticai_api/io/recordio_reader.py
elasticai_api/proto/__init__.py
elasticai_api/proto/elasticai_api_pb2.py
elasticai_api/proto/elasticai_api_pb2_grpc.py
elasticai_api/pytorch/__init__.py
elasticai_api/pytorch/controller.py
elasticai_api/pytorch/dataset.py
elasticai_api/pytorch/optimizer.py
elasticai_api/tensorflow/__init__.py
elasticai_api/tensorflow/controller.py
elasticai_api/tensorflow/optimizer.py
elasticai_api/util/__init__.py
elasticai_api/util/grpc_utils.py
elasticai_api/util/log_utils.py
elasticdl_api-1.0.0.dist-info/DESCRIPTION.rst
elasticdl_api-1.0.0.dist-info/METADATA
elasticdl_api-1.0.0.dist-info/RECORD
elasticdl_api-1.0.0.dist-info/WHEEL
elasticdl_api-1.0.0.dist-info/metadata.json
elasticdl_api-1.0.0.dist-info/top_level.txt
