Metadata-Version: 2.0
Name: elasticdl-api
Version: 1.0.0
Summary: The model development api for ElasticDL.
Home-page: https://elasticdl.org
Author: Ant Group
License: UNKNOWN
Platform: UNKNOWN
Requires-Python: >=3.5
Provides-Extra: tensorflow
Provides-Extra: pytorch
Requires-Dist: grpcio (==1.34.1)
Requires-Dist: grpcio-tools (==1.34.1)
Requires-Dist: protobuf (>=3.12.0)
Requires-Dist: psutil
Provides-Extra: pytorch
Requires-Dist: torch; extra == 'pytorch'
Provides-Extra: tensorflow
Requires-Dist: tensorflow; extra == 'tensorflow'
